{
  "required": true,
  "minVersion": "0.8",
  "package": "de.johni0702.minecraft.bobby.mixin",
  "compatibilityLevel": "JAVA_16",
  "plugin": "de.johni0702.minecraft.bobby.MixinConfigPlugin",
  "client": [
    "BiomeAccessAccessor",
    "ChunkLightProviderMixin",
    "ClientChunkManagerMixin",
    "GameOptionsMixin",
    "GameRendererMixin",
    "IntegratedServerMixin",
    "MinecraftClientMixin",
    "VersionedChunkStorageAccessor",
    "sodium.SodiumChunkManagerMixin",
    "sodium.SodiumGameOptionPagesMixin"
  ],
  "injectors": {
    "defaultRequire": 1
  }
}
